PyDictionary/__init__.py
PyDictionary/core.py
PyDictionary/script.py
PyDictionary/test_pydictionary.py
PyDictionary/utils.py
PyDictionary-2.0.0.dist-info/LICENSE
PyDictionary-2.0.0.dist-info/METADATA
PyDictionary-2.0.0.dist-info/WHEEL
PyDictionary-2.0.0.dist-info/top_level.txt
PyDictionary-2.0.0.dist-info/RECORD
