Metadata-Version: 2.1
Name: PyDictionary
Version: 2.0.0
Summary: A real dictionary module for Python
Home-page: https://github.com/geekpradd/PyDictionary
Author: geekpradd
Author-email: pradd@outlook.com
License: UNKNOWN
Platform: UNKNOWN
Classifier: License :: OSI Approved :: MIT License
Classifier: Operating System :: OS Independent
Requires-Python: >=2.6
Requires-Dist: bs4
Requires-Dist: click
Requires-Dist: goslate
Requires-Dist: requests
